raptors-0.0.2.dist-info/METADATA
raptors-0.0.2.dist-info/WHEEL
raptors/__init__.py
raptors/_raptors.cpython-311-x86_64-linux-gnu.so
raptors-0.0.2.dist-info/RECORD
