Metadata-Version: 2.4
Name: raptors
Version: 0.0.2
Classifier: Development Status :: 2 - Pre-Alpha
Classifier: Intended Audience :: Science/Research
Classifier: License :: OSI Approved :: MIT License
Classifier: Programming Language :: Python :: 3
Classifier: Programming Language :: Rust
Classifier: Topic :: Scientific/Engineering
Summary: Rust-powered, NumPy-compatible array library scaffold.
Author-email: Odos Matthews <odosmatthews@gmail.com>
Requires-Python: >=3.9
Project-URL: Homepage, https://github.com/eddiethedean/raptors
Project-URL: Source, https://github.com/eddiethedean/raptors
Project-URL: Issue Tracker, https://github.com/eddiethedean/raptors/issues
